spotifyflaskdownloader/__init__.py
spotifyflaskdownloader/spotify.py
spotifyflaskdownloader/youtube.py
spotify_flask_downloader-0.0.2.dist-info/LICENSE
spotify_flask_downloader-0.0.2.dist-info/METADATA
spotify_flask_downloader-0.0.2.dist-info/WHEEL
spotify_flask_downloader-0.0.2.dist-info/top_level.txt
spotify_flask_downloader-0.0.2.dist-info/RECORD
