Metadata-Version: 2.1
Name: spotify-flask-downloader
Version: 0.0.2
Summary: A Flask based backend to search & download music from Spotify
Home-page: https://github.com/alexmercerind/react-python-spotify
Author: Hitesh Kumar Saini
Author-email: saini123hitesh@gmail.com
License: UNKNOWN
Platform: UNKNOWN
Classifier: Programming Language :: Python :: 3
Classifier: License :: OSI Approved :: MIT License
Classifier: Operating System :: OS Independent
Requires-Python: >=3.6
Requires-Dist: youtube-search-python
Requires-Dist: flask
Requires-Dist: youtube-dl
Requires-Dist: flask-cors
